pythonexercises/__init__.py
pythonexercises/app_guide.md
pythonexercises/exercises.json
pythonexercises/nums.txt
pythonexercises/python_exercises.css
pythonexercises/python_exercises.py
pythonexercises/quiz.txt
pythonexercises/exercises/6by7.py
pythonexercises/exercises/add_time_strings.py
pythonexercises/exercises/alphabetic_ordering.py
pythonexercises/exercises/character_diff.py
pythonexercises/exercises/count_nested_braces.py
pythonexercises/exercises/dictionary_sort.py
pythonexercises/exercises/first_occurrence.py
pythonexercises/exercises/fstring_braces.py
pythonexercises/exercises/inner_product.py
pythonexercises/exercises/int_length.py
pythonexercises/exercises/iterable_duplicates.py
pythonexercises/exercises/list_of_words.py
pythonexercises/exercises/longest_words.py
pythonexercises/exercises/min_max_iter.py
pythonexercises/exercises/numeric_palindrome.py
pythonexercises/exercises/product_of_nums.py
pythonexercises/exercises/sort_even_odd.py
pythonexercises/exercises/square_cube.py
pythonexercises/exercises/str_comparison.py
pythonexercises/exercises/str_same_letters.py
pythonexercises/exercises/string_slices.py
pythonexercises/exercises/string_styling.py
pythonexercises/exercises/sum_column.py
pythonexercises/exercises/sum_file_numbers.py
pythonexercises/exercises/sum_numbers.py
pythonexercises/sample_files/f1.txt
pythonexercises/sample_files/f2.txt
pythonexercises/sample_files/f3.txt
pythonexercises/sample_files/n1.txt
pythonexercises/solutions/6by7.py
pythonexercises/solutions/add_time_strings.py
pythonexercises/solutions/alphabetic_ordering.py
pythonexercises/solutions/character_diff.py
pythonexercises/solutions/count_nested_braces.py
pythonexercises/solutions/dictionary_sort.py
pythonexercises/solutions/first_occurrence.py
pythonexercises/solutions/fstring_braces.py
pythonexercises/solutions/inner_product.py
pythonexercises/solutions/int_length.py
pythonexercises/solutions/iterable_duplicates.py
pythonexercises/solutions/list_of_words.py
pythonexercises-1.0.0.dist-info/METADATA
pythonexercises-1.0.0.dist-info/WHEEL
pythonexercises-1.0.0.dist-info/entry_points.txt
pythonexercises-1.0.0.dist-info/licenses/LICENSE
pythonexercises-1.0.0.dist-info/RECORD
