Metadata-Version: 2.3
Name: pythonexercises
Version: 1.0.0
Summary: exercises and quiz for beginner-intermediate level Python learners
Project-URL: Source, https://github.com/learnbyexample/TUI-apps/tree/main/PythonExercises
Project-URL: Issues, https://github.com/learnbyexample/TUI-apps/issues
Author-email: Sundeep Agarwal <learnbyexample.net@gmail.com>
Classifier: License :: OSI Approved :: MIT License
Classifier: Operating System :: OS Independent
Classifier: Programming Language :: Python :: 3
Requires-Python: >=3.9
Requires-Dist: textual[syntax]==0.85.2
